{
  "id": "8cOepGXo42",
  "data": {
    "content": {
      "type": "doc",
      "content": [
        {
          "type": "heading",
          "attrs": {
            "level": 3,
            "textAlign": "left"
          },
          "content": [
            {
              "text": "Be informed",
              "type": "text"
            }
          ]
        },
        {
          "type": "paragraph",
          "attrs": {
            "textAlign": "left"
          },
          "content": [
            {
              "text": "Design with continuous learning from user interactions and behaviors.",
              "type": "text"
            }
          ]
        },
        {
          "type": "paragraph",
          "attrs": {
            "textAlign": "left"
          }
        }
      ]
    }
  },
  "size": "small",
  "blockType": "text-editor"
}
