{
  "id": "VfN5P6R3AJ",
  "data": {
    "content": {
      "type": "doc",
      "content": [
        {
          "type": "paragraph",
          "attrs": {
            "textAlign": "left"
          },
          "content": [
            {
              "text": "Use ",
              "type": "text"
            },
            {
              "text": "add",
              "type": "text",
              "marks": [
                {
                  "type": "italic"
                }
              ]
            },
            {
              "text": " to mean adding a thing or person that already exists. For example, if you're adding an existing user to your database, use \"add.\" If the user doesn't exist yet, use ",
              "type": "text"
            },
            {
              "text": "create",
              "type": "text",
              "marks": [
                {
                  "type": "link",
                  "attrs": {
                    "rel": "noopener noreferrer nofollow",
                    "href": "#create",
                    "class": null
                  }
                },
                {
                  "type": "underline"
                }
              ]
            },
            {
              "text": ".",
              "type": "text"
            }
          ]
        }
      ]
    }
  },
  "blockType": "text-editor"
}
