{
  "id": "u1iWOBrbZ9",
  "data": {
    "content": {
      "type": "doc",
      "content": [
        {
          "type": "paragraph",
          "attrs": {
            "textAlign": "left"
          },
          "content": [
            {
              "text": "Use alerts for important information only. Overusing them can result in desensitization. For example, users may develop fatigue and stop paying attention to any of the alerts. ",
              "type": "text"
            }
          ]
        }
      ]
    }
  },
  "blockType": "text-editor"
}
