{
  "id": "SbIL588Aqk",
  "data": {
    "content": {
      "type": "doc",
      "content": [
        {
          "type": "paragraph",
          "attrs": {
            "textAlign": "left"
          },
          "content": [
            {
              "text": "Use ",
              "type": "text"
            },
            {
              "text": "available",
              "type": "text",
              "marks": [
                {
                  "type": "italic"
                }
              ]
            },
            {
              "text": " when referring to a full-color screen component rather than enabled or active.  ",
              "type": "text"
            }
          ]
        }
      ]
    }
  },
  "blockType": "text-editor"
}
