{
  "id": "D8CJGJAsur",
  "data": {
    "content": {
      "type": "doc",
      "content": [
        {
          "type": "heading",
          "attrs": {
            "level": 4,
            "textAlign": "left"
          },
          "content": [
            {
              "text": "Categorization",
              "type": "text",
              "marks": [
                {
                  "type": "bold"
                }
              ]
            }
          ]
        },
        {
          "type": "paragraph",
          "attrs": {
            "textAlign": "left"
          },
          "content": [
            {
              "text": "Primary actions",
              "type": "text",
              "marks": [
                {
                  "type": "bold"
                }
              ]
            },
            {
              "text": ": Use prominent buttons for essential actions.",
              "type": "text"
            }
          ]
        },
        {
          "type": "paragraph",
          "attrs": {
            "textAlign": "left"
          },
          "content": [
            {
              "text": "Secondary actions",
              "type": "text",
              "marks": [
                {
                  "type": "bold"
                }
              ]
            },
            {
              "text": ": Employ smaller icons for less frequent tasks.",
              "type": "text"
            }
          ]
        }
      ]
    }
  },
  "blockType": "text-editor",
  "size": "small"
}
