{
  "id": "0XzxlJfMB7",
  "data": {
    "content": {
      "type": "doc",
      "content": [
        {
          "type": "heading",
          "attrs": {
            "level": 2,
            "textAlign": "left"
          },
          "content": [
            {
              "text": "data cardinality, data center, data mining, data model, data node, data stream, data type",
              "type": "text",
              "marks": [
                {
                  "type": "bold"
                }
              ]
            }
          ]
        },
        {
          "type": "paragraph",
          "attrs": {
            "textAlign": "left"
          },
          "content": [
            {
              "text": "Two words, lowercase, no hyphen.",
              "type": "text"
            }
          ]
        }
      ]
    }
  },
  "blockType": "text-editor"
}
