{
  "id": "jtEcfYV8nP",
  "data": {
    "content": {
      "type": "doc",
      "content": [
        {
          "type": "heading",
          "attrs": {
            "level": 1,
            "textAlign": "left"
          },
          "content": [
            {
              "text": "Typography",
              "type": "text"
            }
          ]
        },
        {
          "type": "paragraph",
          "attrs": {
            "textAlign": "left"
          },
          "content": [
            {
              "text": "Use these text styles for button:",
              "type": "text"
            }
          ]
        },
        {
          "type": "orderedList",
          "attrs": {
            "start": 1
          },
          "content": [
            {
              "type": "listItem",
              "content": [
                {
                  "type": "paragraph",
                  "attrs": {
                    "textAlign": "left"
                  },
                  "content": [
                    {
                      "text": "button",
                      "type": "text"
                    }
                  ]
                }
              ]
            }
          ]
        }
      ]
    }
  },
  "blockType": "text-editor",
  "size": "small"
}
