{
  "id": "stBlCXV8uA",
  "data": {
    "content": {
      "type": "doc",
      "content": [
        {
          "type": "heading",
          "attrs": {
            "level": 2,
            "textAlign": "left"
          },
          "content": [
            {
              "text": "AG",
              "type": "text",
              "marks": [
                {
                  "type": "bold"
                }
              ]
            }
          ]
        },
        {
          "type": "paragraph",
          "attrs": {
            "textAlign": "left"
          },
          "content": [
            {
              "text": "Acronym for ",
              "type": "text"
            },
            {
              "text": "Allocation Group",
              "type": "text",
              "marks": [
                {
                  "type": "link",
                  "attrs": {
                    "rel": "noopener noreferrer nofollow",
                    "href": "#allocation-group",
                    "class": null
                  }
                }
              ]
            },
            {
              "text": ".",
              "type": "text"
            }
          ]
        }
      ]
    }
  },
  "blockType": "text-editor"
}
