{
  "id": "ygLuYYKAY4",
  "data": {
    "guidelines": [
      {
        "id": "GaxYHcN34",
        "type": "do",
        "content": {
          "type": "doc",
          "content": [
            {
              "type": "paragraph",
              "content": [
                {
                  "text": "Turn on notifications.",
                  "type": "text"
                }
              ]
            },
            {
              "type": "paragraph",
              "content": [
                {
                  "text": "Switch to dark mode.",
                  "type": "text"
                }
              ]
            }
          ]
        }
      },
      {
        "id": "GOmfBzaqT",
        "type": "dont",
        "content": {
          "type": "doc",
          "content": [
            {
              "type": "paragraph",
              "content": [
                {
                  "text": "Toggle notifications on and off.",
                  "type": "text"
                }
              ]
            },
            {
              "type": "paragraph",
              "content": [
                {
                  "text": "Toggle from light mode to dark mode.",
                  "type": "text"
                }
              ]
            }
          ]
        }
      }
    ],
    "tileStyles": {
      "imageSize": "none"
    }
  },
  "blockType": "guidelines"
}
