{
  "id": "lumqUtE6C7",
  "data": {
    "content": {
      "type": "doc",
      "content": [
        {
          "type": "heading",
          "attrs": {
            "level": 2,
            "textAlign": "left"
          },
          "content": [
            {
              "text": "class",
              "type": "text",
              "marks": [
                {
                  "type": "bold"
                }
              ]
            }
          ]
        }
      ]
    }
  },
  "blockType": "text-editor"
}
