{
  "id": "boILoye9Gi",
  "title": "Main",
  "type": "data",
  "patternId": "menu",
  "templateId": "web-components-hY3y1MyhrP",
  "data": {
    "props": {
      "open": true
    },
    "slots": {
      "default": [
        {
          "type": "template-demo",
          "demoId": "qgGc8WUNHQ",
          "patternId": "list-item",
          "templateId": "web-components-ytRTf8wtxn"
        },
        {
          "type": "template-demo",
          "demoId": "qgGc8WUNHQ",
          "patternId": "list-item",
          "templateId": "web-components-ytRTf8wtxn"
        },
        {
          "type": "template-demo",
          "demoId": "qgGc8WUNHQ",
          "patternId": "list-item",
          "templateId": "web-components-ytRTf8wtxn"
        }
      ]
    }
  }
}
