{
  "id": "alert",
  "title": "Alert",
  "description": "Notification informing users about important information or events.",
  "statuses": {},
  "templates": [
    {
      "id": "web-components-4qjJYWsUZi",
      "title": "Web components",
      "path": "../../../dist/libs/components/alert.mjs",
      "alias": "cv-alert",
      "templateLanguageId": "web-components",
      "spec": {
        "props": {
          "$schema": "http://json-schema.org/draft-07/schema",
          "description": "",
          "type": "object",
          "required": [],
          "properties": {
            "icon": {
              "type": "string",
              "default": "info",
              "description": "Icon added to the alert"
            },
            "state": {
              "description": "State representation which can take the values:\nactive|negative|positive|caution",
              "type": "string",
              "enum": ["active", "negative", "positive", "caution"]
            },
            "inline": {
              "type": "boolean",
              "description": "Displays the alert inline with its container"
            },
            "titleText": {
              "type": "string",
              "default": "Alert title",
              "description": "Title of the alert"
            },
            "iconAriaLabel": {
              "type": "string",
              "default": "aria-label for the icon",
              "description": "aria-label for the icon"
            },
            "descriptionText": {
              "type": "string",
              "default": "Alert description",
              "description": "Description of the alert"
            }
          }
        },
        "slots": {
          "action-items": {
            "allowedPatternIds": ["button", "checkbox"],
            "title": "action-items",
            "description": "Action items that can be added to the alert"
          }
        }
      },
      "demoIds": [
        "tnvgSz6pjh",
        "vmDFzhOhSn",
        "S4K35ZGdnu",
        "WosGIC3IsN",
        "t7e3P48Pkm",
        "pYd0j3oNrI",
        "xnEh2A2lis",
        "LATgTeg21H",
        "yf2q5F2Jyk",
        "CE5x5TaMa2",
        "s8Ci4Cd08W"
      ],
      "blockIds": ["RILkEnTgSL", "av87gquwW3", "pbJlBMxTth"]
    }
  ],
  "tabs": [
    {
      "id": "overview",
      "type": "subPage"
    },
    {
      "id": "syFSN1SPG",
      "type": "subPage"
    },
    {
      "id": "web-components-4qjJYWsUZi",
      "type": "template"
    },
    {
      "id": "VFcB0OS3SY",
      "type": "designSrc",
      "hidden": true
    }
  ],
  "subPages": [
    {
      "id": "overview",
      "title": "Usage",
      "blockIds": [
        "k3y6F49bYx",
        "lNmJbVwFSG",
        "vknOWbT5Uz",
        "79hYuB9zmU",
        "UIzn6dTrAs",
        "JjTPPE7SJr",
        "mlMyDNdc",
        "ChOAoD1GAW",
        "IqfDGKonyI",
        "8pPRWGTRAH",
        "Dx-Uvpxsf5",
        "m2ZD8JXZJo",
        "FMTBoRTSjq",
        "VQ8pVCy6i6",
        "QnQPi8qWz0",
        "Ufyw8Ka0Dm"
      ]
    },
    {
      "id": "syFSN1SPG",
      "title": "Style",
      "blockIds": [
        "0rZ0OosspG",
        "bKlWE2O54",
        "yK1IYXpcjU",
        "ti7Lni7UG4",
        "ypfZwjL-y5",
        "lGjAXK98hR",
        "Zu6MbzLgVg",
        "IFK9GoKApE",
        "lORqKBgsh4",
        "ZI8Csk1wp8",
        "nHhPPOGfai",
        "VlWhJxQNN",
        "5zEc7Rugg",
        "8dIrflX3f9",
        "nre5fjvPZk",
        "ancMEaFQ1D",
        "J5SoJSRiCJ",
        "LfuARn1i5z",
        "bjwP36baZI",
        "4EvigbwHZS",
        "ML4KBVvZwi",
        "xLJBXfBR6E",
        "6RPFpTE9sB",
        "qIHJvwBfU",
        "TrERoIk0Wp",
        "a6InsrLwTc"
      ]
    }
  ],
  "designSrcComponentsById": {
    "VFcB0OS3SY": {
      "id": "VFcB0OS3SY",
      "title": "Figma Component",
      "fileId": "KvXVAmYdCVAS7hzkOa73Em",
      "componentId": "7727:15659"
    }
  },
  "settings": {
    "pageHeader": {
      "backgroundColor": {
        "type": "design-token",
        "tokenName": "surface-variant"
      },
      "textColorDescription": {
        "type": "design-token",
        "tokenName": "on-surface-variant"
      },
      "textColorTitle": {
        "type": "design-token",
        "tokenName": "on-surface"
      }
    }
  }
}
