{
  "id": "menu-2auajeekzb",
  "tabs": [
    {
      "id": "overview",
      "type": "subPage"
    },
    {
      "id": "LjKvhx5Lkz",
      "type": "subPage"
    },
    {
      "id": "RwoYygHU46",
      "type": "subPage"
    },
    {
      "id": "xfprdvFw5M",
      "type": "designSrc"
    },
    {
      "id": "web-components-hY3y1MyhrP",
      "type": "template"
    }
  ],
  "title": "Menu (no web component)",
  "statuses": {},
  "subPages": [
    {
      "id": "overview",
      "title": "Usage",
      "blockIds": [
        "jNiYbHMSbL",
        "1B3Vx1PzV2",
        "i-gv5rf8EW",
        "prldZnTHgw",
        "xiDUfg987c",
        "mpYEXAad7g",
        "LaDKdnyImC",
        "bYouynBIao",
        "70LmYLbEtT"
      ]
    },
    {
      "id": "LjKvhx5Lkz",
      "title": "Style",
      "blockIds": [
        "qFCzRPrV3",
        "aKL4FnzGco",
        "a8rNjR7Rr1",
        "fPGkVLxlOw",
        "iI1Nyaoe8J",
        "Vue4grbdA",
        "ryWiwearP",
        "1HnB7sbgRm",
        "np6PYCkbE",
        "oI-ka9MEjZ",
        "lSs0JoynGf",
        "5sdRUSegm7",
        "QVIz25kKPE",
        "7wtSK9N0T8",
        "jOCacLPaWp",
        "LxxrI6e5uu",
        "041HcbISHW",
        "B3brz3Uq8",
        "B2GTydGeMR",
        "Kcfh1ONyLb",
        "i5r5rWMLXX",
        "KS3XB0w2fg",
        "7bwqSbXFP5",
        "9HMxsYJr4r",
        "NVZUyrBgdq",
        "jpOIPFitXa",
        "mxDC6QnoSU",
        "hmzaZQYDQ",
        "nIpMIzvWnr",
        "Uy3GtEB0eV",
        "hVphhChmrx",
        "b4DSxOAVh",
        "mZsu4Je12W",
        "3-vpgFGvpi",
        "pNnWNgzyQu",
        "U35p7gUFR9",
        "u4zcTb04C",
        "X4y4jknpft",
        "RC2JwgxmNW",
        "3aABw1L0W9",
        "trmoE3ahXH",
        "QyTP6f2pCn",
        "U8srTT6uRd",
        "bnpJvv9Ekf",
        "K5HNBzE2vP",
        "EmuNh2cCK",
        "UGLfVJbUTS",
        "3ZeA8SLHP1"
      ]
    },
    {
      "id": "RwoYygHU46",
      "title": "Accessibility",
      "blockIds": [
        "8J63d4rxJh",
        "JMfZ6qgH2U",
        "NRrO40LwG",
        "0qBPRNGa9E",
        "HYCt-WfYzt",
        "gLIFIuxJ6p",
        "TfjCtSVFmq",
        "6X53dXG9lc"
      ]
    }
  ],
  "templates": [
    {
      "id": "web-components-hY3y1MyhrP",
      "title": "Web components",
      "path": "../../../dist/libs/components/menu.mjs",
      "alias": "cv-menu",
      "templateLanguageId": "web-components",
      "spec": {
        "slots": {
          "default": {
            "allowedPatternIds": ["list-item"],
            "title": "default",
            "disallowText": true,
            "description": "Content to display in the menus internal <cv-list> element."
          }
        },
        "props": {
          "$schema": "http://json-schema.org/draft-07/schema",
          "description": "",
          "type": "object",
          "required": [],
          "properties": {
            "open": {
              "type": "boolean",
              "default": true,
              "description": "Opens the menu."
            },
            "anchor": {
              "type": "string",
              "description": "Determines from which element the floating menu should calculate sizing and position offsets. In the default case, both mwc-menu and the anchor should share a parent with position:relative. Changing anchor typically requires absolute or fixed. Takes one of: HTMLElement | null"
            },
            "corner": {
              "type": "string",
              "enum": [
                "TOP_LEFT",
                "TOP_RIGHT",
                "BOTTOM_LEFT",
                "BOTTOM_RIGHT",
                "TOP_START",
                "TOP_END",
                "BOTTOM_START",
                "BOTTOM_END"
              ]
            },
            "menuCorner": {
              "description": "Horizontal corner of the menu from which the menu should position itself. NOTE: Only horizontal corners are supported.",
              "type": "string",
              "enum": ["START", "END"]
            },
            "x": {
              "description": "Sets horizontal position when absolute. When given an anchor, sets horizontal position relative to anchor at given corner. Requires y not to be null.",
              "type": "number"
            },
            "y": {
              "description": "Sets vertical position when absolute. When given an anchor, sets vertical position relative to anchor at given corner. Requires x not to be null.",
              "type": "number"
            },
            "defaultFocus": {
              "description": "Item to focus upon menu open.",
              "type": "string",
              "enum": ["NONE", "LIST_ROOT", "FIRST_ITEM", "LAST_ITEM"]
            },
            "innerAriaLabel": {
              "type": "string",
              "description": "Proxies to cv-list's innerAriaLabel property."
            },
            "innerRole": {
              "description": "Proxies to cv-list's innerRole property",
              "type": "string",
              "enum": ["menu", "listbox"]
            },
            "quick": {
              "description": "Whether to skip the opening animation.",
              "type": "boolean"
            },
            "absolute": {
              "description": "Makes the menu's position absolute which will be relative to whichever ancestor has position:relative. Setting x and y will modify the menu's left and top. Setting anchor will attempt to position the menu to the anchor.",
              "type": "boolean"
            },
            "fixed": {
              "description": "Makes the menu's position fixed which will be relative to the window. Setting x and y will modify the menu's left and top. Setting anchor will attempt to position the menu to the anchor's immediate position before opening.",
              "type": "boolean"
            },
            "forceGroupSelection": {
              "description": "Forces a menu group to have a selected item by preventing deselection of menu items in menu groups via user interaction.",
              "type": "boolean"
            },
            "fullwidth": {
              "description": "Sets surface width to 100%.",
              "type": "boolean"
            },
            "stayOpenOnBodyClick": {
              "description": "Prevents the menu from closing when clicking outside the menu.",
              "type": "boolean"
            },
            "wrapFocus": {
              "description": "Proxies to cv-list's wrapFocus property.",
              "type": "boolean"
            },
            "multi": {
              "description": "Proxies to cv-list's multi property.",
              "type": "boolean"
            },
            "activatable": {
              "description": "Proxies to cv-list's activatable property.",
              "type": "boolean"
            }
          }
        }
      },
      "demoIds": ["boILoye9Gi"],
      "blockIds": [
        "MNWCL2mIGs",
        "dPlJPL5Jcu",
        "JbCt0FJ6u",
        "MVgOOr6WnP",
        "0dX3ojt8-P",
        "HYX-451UaR"
      ]
    }
  ],
  "description": "Provide extended features or hide some items for usability.",
  "designSrcComponentsById": {
    "xfprdvFw5M": {
      "id": "xfprdvFw5M",
      "title": "Figma Component",
      "fileId": "KvXVAmYdCVAS7hzkOa73Em",
      "componentId": "7605:20819"
    }
  }
}
